jokerLang/__init__.py
jokerLang/joker.py
jokerLang-1.0.5.dist-info/METADATA
jokerLang-1.0.5.dist-info/WHEEL
jokerLang-1.0.5.dist-info/top_level.txt
jokerLang-1.0.5.dist-info/RECORD
