Metadata-Version: 2.1
Name: jokerLang
Version: 1.0.5
Summary: Hello,welcome to my field
Author: jokerLang
Author-email: 524276169@qq.com
License: MIT
Keywords: joker
Platform: all
